astx_transpilers/__init__.py
astx_transpilers/py.typed
astx_transpilers/python_string.py
astx_transpilers/python_to_ast.py
astx_transpilers-0.23.1.dist-info/METADATA
astx_transpilers-0.23.1.dist-info/WHEEL
astx_transpilers-0.23.1.dist-info/RECORD
