Metadata-Version: 2.3
Name: astx-transpilers
Version: 0.23.1
Summary: ASTx is an agnostic expression structure for AST.
License: BSD 3 Clause
Author: Ivan Ogasawara
Author-email: ivan.ogasawara@gmail.com
Requires-Python: >=3.9,<4
Classifier: License :: Other/Proprietary License
Classifier: Programming Language :: Python :: 3
Classifier: Programming Language :: Python :: 3.9
Classifier: Programming Language :: Python :: 3.10
Classifier: Programming Language :: Python :: 3.11
Classifier: Programming Language :: Python :: 3.12
Classifier: Programming Language :: Python :: 3.13
Requires-Dist: astx (==0.23.1)
Requires-Dist: atpublic (>=4.0)
Requires-Dist: eval-type-backport (>=0.2) ; python_version < "3.10"
Requires-Dist: plum-dispatch (>=2)
Requires-Dist: typeguard (>=4)
